jams_convertor/__init__.py
jams_convertor/jams_convertor.py
jams_convertor-0.1.2.dist-info/LICENSE
jams_convertor-0.1.2.dist-info/METADATA
jams_convertor-0.1.2.dist-info/WHEEL
jams_convertor-0.1.2.dist-info/top_level.txt
jams_convertor-0.1.2.dist-info/RECORD
